pinakinathc_py/__init__.py
pinakinathc_py/send_email.py
torchscope/__init__.py
torchscope/helper.py
torchscope/scope.py
pinakinathc_py-0.0.2.dist-info/LICENSE
pinakinathc_py-0.0.2.dist-info/METADATA
pinakinathc_py-0.0.2.dist-info/WHEEL
pinakinathc_py-0.0.2.dist-info/top_level.txt
pinakinathc_py-0.0.2.dist-info/RECORD
